pymemdb/__init__.py
pymemdb/column.py
pymemdb/database.py
pymemdb/errors.py
pymemdb/table.py
pymemdb-1.4.3.dist-info/LICENSE
pymemdb-1.4.3.dist-info/WHEEL
pymemdb-1.4.3.dist-info/METADATA
pymemdb-1.4.3.dist-info/RECORD
