Metadata-Version: 2.1
Name: pymemdb
Version: 1.4.3
Summary: A very fast in-memory database with export to sqlite written purely in python
Home-page: https://github.com/luerhard/pymemdb/
License: MIT
Author: Lukas Erhard
Author-email: luerhard@googlemail.com
Requires-Python: >=3.6
Classifier: License :: OSI Approved :: MIT License
Classifier: Programming Language :: Python :: 3.6
Classifier: Programming Language :: Python :: 3.7
Classifier: Programming Language :: Python :: 3.8
Classifier: Development Status :: 3 - Alpha
Classifier: Topic :: Utilities
Requires-Dist: dataset
Requires-Dist: pytest ; extra == "dev"
Requires-Dist: pytest-cov ; extra == "dev"
Requires-Dist: bumpversion ; extra == "dev"
Provides-Extra: dev
